edrn/__init__.py
edrn/bmdb/__init__.py
edrn/bmdb/testing/VERSION.txt
edrn/bmdb/testing/__init__.py
edrn/bmdb/testing/main.py
edrn/bmdb/testing/__pycache__/__init__.cpython-311.pyc
edrn/bmdb/testing/data/__init__.py
edrn/bmdb/testing/data/biomarker-organs.rdf
edrn/bmdb/testing/data/biomarkers.rdf
edrn/bmdb/testing/data/publications.rdf
edrn/bmdb/testing/data/resources.rdf
edrn.bmdb.testing-0.0.0.dist-info/LICENSE.md
edrn.bmdb.testing-0.0.0.dist-info/METADATA
edrn.bmdb.testing-0.0.0.dist-info/WHEEL
edrn.bmdb.testing-0.0.0.dist-info/entry_points.txt
edrn.bmdb.testing-0.0.0.dist-info/top_level.txt
edrn.bmdb.testing-0.0.0.dist-info/RECORD
